[
    {
        "id": 1,
        "content": "fn",
        "prop": "kw_fn",
        "loc": {
            "row": 1,
            "col": 1
        }
    },
    {
        "id": 2,
        "content": "program_5_4__1",
        "prop": "identifier",
        "loc": {
            "row": 1,
            "col": 4
        }
    },
    {
        "id": 3,
        "content": "(",
        "prop": "l_paren",
        "loc": {
            "row": 1,
            "col": 18
        }
    },
    {
        "id": 4,
        "content": ")",
        "prop": "r_paren",
        "loc": {
            "row": 1,
            "col": 19
        }
    },
    {
        "id": 5,
        "content": "{",
        "prop": "l_brace",
        "loc": {
            "row": 1,
            "col": 21
        }
    },
    {
        "id": 6,
        "content": "while",
        "prop": "kw_while",
        "loc": {
            "row": 2,
            "col": 1
        }
    },
    {
        "id": 7,
        "content": "1",
        "prop": "integer_constant",
        "loc": {
            "row": 2,
            "col": 7
        }
    },
    {
        "id": 8,
        "content": "==",
        "prop": "equalequal",
        "loc": {
            "row": 2,
            "col": 8
        }
    },
    {
        "id": 9,
        "content": "0",
        "prop": "integer_constant",
        "loc": {
            "row": 2,
            "col": 10
        }
    },
    {
        "id": 10,
        "content": "{",
        "prop": "l_brace",
        "loc": {
            "row": 2,
            "col": 12
        }
    },
    {
        "id": 11,
        "content": "continue",
        "prop": "kw_continue",
        "loc": {
            "row": 3,
            "col": 1
        }
    },
    {
        "id": 12,
        "content": ";",
        "prop": "semi",
        "loc": {
            "row": 3,
            "col": 9
        }
    },
    {
        "id": 13,
        "content": "}",
        "prop": "r_brace",
        "loc": {
            "row": 4,
            "col": 1
        }
    },
    {
        "id": 14,
        "content": "}",
        "prop": "r_brace",
        "loc": {
            "row": 5,
            "col": 1
        }
    },
    {
        "id": 15,
        "content": "fn",
        "prop": "kw_fn",
        "loc": {
            "row": 6,
            "col": 1
        }
    },
    {
        "id": 16,
        "content": "program_5_4__2",
        "prop": "identifier",
        "loc": {
            "row": 6,
            "col": 4
        }
    },
    {
        "id": 17,
        "content": "(",
        "prop": "l_paren",
        "loc": {
            "row": 6,
            "col": 18
        }
    },
    {
        "id": 18,
        "content": ")",
        "prop": "r_paren",
        "loc": {
            "row": 6,
            "col": 19
        }
    },
    {
        "id": 19,
        "content": "{",
        "prop": "l_brace",
        "loc": {
            "row": 6,
            "col": 21
        }
    },
    {
        "id": 20,
        "content": "while",
        "prop": "kw_while",
        "loc": {
            "row": 7,
            "col": 1
        }
    },
    {
        "id": 21,
        "content": "1",
        "prop": "integer_constant",
        "loc": {
            "row": 7,
            "col": 7
        }
    },
    {
        "id": 22,
        "content": "==",
        "prop": "equalequal",
        "loc": {
            "row": 7,
            "col": 8
        }
    },
    {
        "id": 23,
        "content": "1",
        "prop": "integer_constant",
        "loc": {
            "row": 7,
            "col": 10
        }
    },
    {
        "id": 24,
        "content": "{",
        "prop": "l_brace",
        "loc": {
            "row": 7,
            "col": 12
        }
    },
    {
        "id": 25,
        "content": "break",
        "prop": "kw_break",
        "loc": {
            "row": 8,
            "col": 1
        }
    },
    {
        "id": 26,
        "content": ";",
        "prop": "semi",
        "loc": {
            "row": 8,
            "col": 6
        }
    },
    {
        "id": 27,
        "content": "}",
        "prop": "r_brace",
        "loc": {
            "row": 9,
            "col": 1
        }
    },
    {
        "id": 28,
        "content": "}",
        "prop": "r_brace",
        "loc": {
            "row": 10,
            "col": 1
        }
    },
    {
        "id": 29,
        "content": "#",
        "prop": "eof",
        "loc": {
            "row": 11,
            "col": 1
        }
    }
]